src/ESTARFM.py
src/ESTARFM_FAST.py
bravooooooo-0.1.dist-info/METADATA
bravooooooo-0.1.dist-info/WHEEL
bravooooooo-0.1.dist-info/top_level.txt
bravooooooo-0.1.dist-info/RECORD
