Metadata-Version: 2.1
Name: bravooooooo
Version: 0.1
Summary: my description
Home-page: UNKNOWN
Author: Luis bravo
Author-email: luisbravocollado@gmail.com
License: UNKNOWN
Keywords: testing,logging,example
Platform: UNKNOWN
